civitai_downloader/__init__.py
civitai_downloader/app.py
civitai_downloader/downloader.py
civitai_downloader-1.3.5.dist-info/LICENSE
civitai_downloader-1.3.5.dist-info/METADATA
civitai_downloader-1.3.5.dist-info/WHEEL
civitai_downloader-1.3.5.dist-info/entry_points.txt
civitai_downloader-1.3.5.dist-info/top_level.txt
civitai_downloader-1.3.5.dist-info/RECORD
