Metadata-Version: 2.1
Name: civitai-downloader
Version: 1.3.5
Summary: A downloader for CivitAI models
Home-page: https://github.com/Ryouko-Yamanda65777/civitai-downloader
Author: Ryouko-Yamanda65777
Author-email: 
Project-URL: Bug Tracker, https://github.com/Ryouko-Yamanda65777/civitai-downloader/issues
Project-URL: Source Code, https://github.com/Ryouko-Yamanda65777/civitai-downloader
Keywords: CivitAI downloader gradio
Classifier: Development Status :: 4 - Beta
Classifier: Programming Language :: Python :: 3
Classifier: License :: OSI Approved :: Apache Software License
Classifier: Operating System :: OS Independent
Classifier: Intended Audience :: Developers
Classifier: Topic :: Software Development :: Libraries :: Python Modules
Requires-Python: >=3.6
License-File: LICENSE
Requires-Dist: gradio
Requires-Dist: pyngrok
